FinMind/__init__.py
FinMind/_version.py
FinMind/crawler/__init__.py
FinMind/crawler/base.py
FinMind/crawler/commodities.py
FinMind/crawler/demo.py
FinMind/crawler/government_bonds.py
FinMind/data/__init__.py
FinMind/data/data_loader.py
FinMind/data/data_subscriber.py
FinMind/data/finmind_api.py
FinMind/indicators/__init__.py
FinMind/indicators/bias.py
FinMind/indicators/continue_holding.py
FinMind/indicators/institutional_investors_follower.py
FinMind/indicators/institutional_investors_over_buy.py
FinMind/indicators/kd.py
FinMind/indicators/kd_crossover.py
FinMind/indicators/ma_cross_orver.py
FinMind/indicators/short_sale_margin_purchase_ratio.py
FinMind/plotting/__init__.py
FinMind/plotting/bar.py
FinMind/plotting/kline.py
FinMind/plotting/line.py
FinMind/plotting/pie.py
FinMind/schema/__init__.py
FinMind/schema/data.py
FinMind/schema/indicators.py
FinMind/schema/info.py
FinMind/schema/plot.py
FinMind/schema/rule.py
FinMind/strategies/__init__.py
FinMind/strategies/base.py
FinMind/strategies/bias.py
FinMind/strategies/continue_holding.py
FinMind/strategies/institutional_investors_follower.py
FinMind/strategies/kd.py
FinMind/strategies/kd_crossover.py
FinMind/strategies/ma_crossover.py
FinMind/strategies/macd_crossover.py
FinMind/strategies/max_min_period_bias.py
FinMind/strategies/naive_kd.py
FinMind/strategies/short_sale_margin_purchase_ratio.py
FinMind/strategies/utils.py
FinMind/templates/post.html
FinMind/utility/__init__.py
FinMind/utility/request.py
FinMind/utility/rule.py
finmind-1.9.4.dist-info/LICENSE
finmind-1.9.4.dist-info/METADATA
finmind-1.9.4.dist-info/WHEEL
finmind-1.9.4.dist-info/top_level.txt
finmind-1.9.4.dist-info/RECORD
