Metadata-Version: 2.1
Name: finmind
Version: 1.9.4
Summary: financial mining
Home-page: https://github.com/FinMind
Author: linsam
Author-email: finmind.tw@gmail.com
Project-URL: documentation, https://finmind.github.io/
Project-URL: Source, https://github.com/FinMind/FinMind
Keywords: financial,python
Classifier: Development Status :: 3 - Alpha
License-File: LICENSE
Requires-Dist: pandas >=1.1.5
Requires-Dist: numpy >=1.19.5
Requires-Dist: requests >=2.23.0
Requires-Dist: pydantic >=1.6.1
Requires-Dist: ta ~=0.5.25
Requires-Dist: pytest >=6.2.2
Requires-Dist: lxml >=4.6.3
Requires-Dist: pyecharts >=1.9.0
Requires-Dist: ipython >=7.16.1
Requires-Dist: loguru >=0.5.3
Requires-Dist: setuptools >=49.2.1
Requires-Dist: aiohttp >=3.7.4.post0
Requires-Dist: flask >=2.0.1
Requires-Dist: importlib-metadata >=4.8.1
Requires-Dist: nest-asyncio >=1.6.0
